{
  "date": "2026-07-02T08:33:06Z",
  "total_products": 20,
  "products": [
    {
      "name": "Tesot Air Fryer Non Stick Baking Paper Liners Disposabl...",
      "price": 167,
      "category": "Home_Kitchen",
      "image_url": "https://rukminim2.flixcart.com/image/612/612/xif0q/airfryer-tray/z/q/0/disposable-air-fryer-paper-liners-8-inch-square-100-count-non-original-imahzfknkzbafgwn.jpeg?q=70",
      "flipkart_url": "https://www.flipkart.com/tesot-air-fryer-non-stick-baking-paper-liners-disposable-100-pcs-airfryer-tray/p/itm98ab91418a0fb?pid=AFTHZGP6G5UXPZGY&lid=LSTAFTHZGP6G5UXPZGYOTJQZK&marketplace=FLIPKART&store=j9e&srno=b_1_1&otracker=browse&fm=organic&iid=9ee4cd9c-6a78-4cd3-874f-85b5477e5524.AFTHZGP6G5UXPZGY.SEARCH&ppt=None&ppn=None&ssid=0n0jcufd1c0000001782980983280&ov_redirect=true&ov_redirect=true",
      "scraped_at": "2026-07-02T08:29:45.176129",
      "quick_analysis": {
        "quick_score": 80,
        "top_pros": [
          "Non Stick",
          "Disposable"
        ],
        "top_con": "No reviews",
        "quick_verdict": "Worth checking"
      }
    },
    {
      "name": "Tesot 100 PCS Disposable Air Fryer Cooking Sheets Squar...",
      "price": 298,
      "category": "Home_Kitchen",
      "image_url": "https://rukminim2.flixcart.com/image/612/612/xif0q/airfryer-tray/u/p/f/100pcs-premium-air-fryer-square-liners-oil-proof-disposable-original-imahgzuea2vn6ghg.jpeg?q=70",
      "flipkart_url": "https://www.flipkart.com/tesot-100-pcs-disposable-air-fryer-cooking-sheets-square-airfryer-tray/p/itm882f43d9ceb47?pid=AFTHZGZZEH4PYGUG&lid=LSTAFTHZGZZEH4PYGUGDC4SNN&marketplace=FLIPKART&store=j9e&srno=b_1_2&otracker=browse&fm=organic&iid=9ee4cd9c-6a78-4cd3-874f-85b5477e5524.AFTHZGZZEH4PYGUG.SEARCH&ppt=None&ppn=None&ssid=0n0jcufd1c0000001782980983280&ov_redirect=true&ov_redirect=true",
      "scraped_at": "2026-07-02T08:29:45.176367",
      "quick_analysis": {
        "quick_score": 80,
        "top_pros": [
          "Easy to use",
          "Convenient"
        ],
        "top_con": "No reviews",
        "quick_verdict": "Worth checking"
      }
    },
    {
      "name": "Pri s 001 Mixer Juicer Jar",
      "price": 251,
      "category": "Home_Kitchen",
      "image_url": "https://rukminim2.flixcart.com/image/612/612/xif0q/mixer-juicer-jar/f/i/c/001-pri-s-1500-original-imahn94f52xuxqus.jpeg?q=70",
      "flipkart_url": "https://www.flipkart.com/pri-s-001-mixer-juicer-jar/p/itm64fef912191dd?pid=MJJHN95MFYGQGWNG&lid=LSTMJJHN95MFYGQGWNGZJEUGQ&marketplace=FLIPKART&store=j9e&srno=b_1_3&otracker=browse&fm=organic&iid=9ee4cd9c-6a78-4cd3-874f-85b5477e5524.MJJHN95MFYGQGWNG.SEARCH&ppt=None&ppn=None&ssid=0n0jcufd1c0000001782980983280&ov_redirect=true&ov_redirect=true",
      "scraped_at": "2026-07-02T08:29:45.176602",
      "quick_analysis": {
        "quick_score": 80,
        "top_pros": [
          "Easy to use",
          "Durable design"
        ],
        "top_con": "Pricey option",
        "quick_verdict": "Worth checking"
      }
    },
    {
      "name": "CONTROLER ACER ANDROID LED TV REMOTE ACER ANDROID LED T...",
      "price": 298,
      "category": "Home_Kitchen",
      "image_url": "https://rukminim2.flixcart.com/image/612/612/xif0q/remote-controller/g/s/o/acer-android-led-tv-remote-controler-original-imahzevjccqxnuhh.jpeg?q=70",
      "flipkart_url": "https://www.flipkart.com/controler-acer-android-led-tv-remote-compatible-controller/p/itmac2bbfc77aefc?pid=REMHZEVJNFFGHMEJ&lid=LSTREMHZEVJNFFGHMEJMVMREN&marketplace=FLIPKART&store=j9e&srno=b_1_4&otracker=browse&fm=organic&iid=9ee4cd9c-6a78-4cd3-874f-85b5477e5524.REMHZEVJNFFGHMEJ.SEARCH&ppt=None&ppn=None&ssid=0n0jcufd1c0000001782980983280&ov_redirect=true&ov_redirect=true",
      "scraped_at": "2026-07-02T08:29:45.176840",
      "quick_analysis": {
        "quick_score": 80,
        "top_pros": [
          "Easy Access",
          "Compatible Device"
        ],
        "top_con": "Limited Reviews",
        "quick_verdict": "Worth checking"
      }
    },
    {
      "name": "Thunderex S5 Air Mouse Remote Control with Voice Comman...",
      "price": 500,
      "category": "Home_Kitchen",
      "image_url": "https://rukminim2.flixcart.com/image/612/612/xif0q/remote-controller/c/t/i/air-mouse-remote-control-with-voice-command-motion-sensing-original-imahzdcy8dz8wfwg.jpeg?q=70",
      "flipkart_url": "https://www.flipkart.com/thunderex-s5-air-mouse-remote-control-voice-command-motion-sensing-gyroscope-fly-2-4ghz-usb-plug-play-controller/p/itma8fe1a0de3b4b?pid=REMHZDCYVRZTWNGA&lid=LSTREMHZDCYVRZTWNGASSM3JW&marketplace=FLIPKART&store=j9e&srno=b_1_5&otracker=browse&fm=organic&iid=9ee4cd9c-6a78-4cd3-874f-85b5477e5524.REMHZDCYVRZTWNGA.SEARCH&ppt=None&ppn=None&ssid=0n0jcufd1c0000001782980983280&ov_redirect=true&ov_redirect=true",
      "scraped_at": "2026-07-02T08:29:45.177117",
      "quick_analysis": {
        "quick_score": 80,
        "top_pros": [
          "Voice Command",
          "Motion Sensing"
        ],
        "top_con": "No reviews",
        "quick_verdict": "Worth checking"
      }
    },
    {
      "name": "Technovate Inverter AC Remote Suitable for Whirlpool Sp...",
      "price": 998,
      "category": "Home_Kitchen",
      "image_url": "https://rukminim2.flixcart.com/image/612/612/xif0q/remote-controller/z/c/a/inverter-ac-remote-suitable-for-whirlpool-split-air-conditioner-original-imahz9rzxfqfqbzz.jpeg?q=70",
      "flipkart_url": "https://www.flipkart.com/technovate-inverter-ac-remote-suitable-whirlpool-split-air-conditioner-100-original-controller/p/itme5a15ed319def?pid=REMHZ9RQSFMFN3VQ&lid=LSTREMHZ9RQSFMFN3VQIYLSKL&marketplace=FLIPKART&store=j9e&srno=b_1_6&otracker=browse&fm=organic&iid=9ee4cd9c-6a78-4cd3-874f-85b5477e5524.REMHZ9RQSFMFN3VQ.SEARCH&ppt=None&ppn=None&ssid=0n0jcufd1c0000001782980983280&ov_redirect=true&ov_redirect=true",
      "scraped_at": "2026-07-02T08:29:45.177338",
      "quick_analysis": {
        "quick_score": 80,
        "top_pros": [
          "Original Remote",
          "Easy Control"
        ],
        "top_con": "No Reviews",
        "quick_verdict": "Worth checking"
      }
    },
    {
      "name": "Thunderex Voltas Smile Remote Compatible with AC Contro...",
      "price": 378,
      "category": "Home_Kitchen",
      "image_url": "https://rukminim2.flixcart.com/image/612/612/xif0q/remote-controller/t/b/b/remote-compatible-with-ac-control-suitable-for-split-window-original-imahz4gjjkwsgcmx.jpeg?q=70",
      "flipkart_url": "https://www.flipkart.com/thunderex-voltas-smile-remote-compatible-ac-control-suitable-split-window-controller/p/itmbf54de829bf05?pid=REMHZ4GKQY2UN9FZ&lid=LSTREMHZ4GKQY2UN9FZRPKQKB&marketplace=FLIPKART&store=j9e&srno=b_1_7&otracker=browse&fm=organic&iid=9ee4cd9c-6a78-4cd3-874f-85b5477e5524.REMHZ4GKQY2UN9FZ.SEARCH&ppt=None&ppn=None&ssid=0n0jcufd1c0000001782980983280&ov_redirect=true&ov_redirect=true",
      "scraped_at": "2026-07-02T08:29:45.177555",
      "quick_analysis": {
        "quick_score": 80,
        "top_pros": [
          "Easy to use",
          "Good price"
        ],
        "top_con": "No reviews",
        "quick_verdict": "Worth checking"
      }
    },
    {
      "name": "Bondora Air Fryer Parchment Paper 100 PCS Square 8 Inch...",
      "price": 154,
      "category": "Home_Kitchen",
      "image_url": "https://rukminim2.flixcart.com/image/612/612/xif0q/airfryer-tray/w/k/3/air-fryer-parchment-paper-100-pcs-square-8-inch-disposable-original-imahzfhggfcnnq3z.jpeg?q=70",
      "flipkart_url": "https://www.flipkart.com/bondora-air-fryer-parchment-paper-100-pcs-square-8-inch-disposable-airfryer-tray/p/itm88f420570b11c?pid=AFTHZFHGNXG7G7WH&lid=LSTAFTHZFHGNXG7G7WHP9PQCR&marketplace=FLIPKART&store=j9e&srno=b_1_8&otracker=browse&fm=organic&iid=9ee4cd9c-6a78-4cd3-874f-85b5477e5524.AFTHZFHGNXG7G7WH.SEARCH&ppt=None&ppn=None&ssid=0n0jcufd1c0000001782980983280&ov_redirect=true&ov_redirect=true",
      "scraped_at": "2026-07-02T08:29:45.177794",
      "quick_analysis": {
        "quick_score": 80,
        "top_pros": [
          "Easy to use",
          "Oil proof"
        ],
        "top_con": "Limited reviews",
        "quick_verdict": "Worth checking"
      }
    },
    {
      "name": "RM AC AR-C484B32 Remote Control LCD Display, Multi-Func...",
      "price": 398,
      "category": "Home_Kitchen",
      "image_url": "https://rukminim2.flixcart.com/image/612/612/xif0q/remote-controller/e/a/u/ac-ar-c484b32-remote-control-lcd-display-multi-function-rm-original-imahz4k24zga9za4.jpeg?q=70",
      "flipkart_url": "https://www.flipkart.com/rm-ac-ar-c484b32-remote-control-lcd-display-multi-function-125-ar-rcd2e-compatible-o-general-split-window-controller/p/itmbc49de42005d7?pid=REMHZ4K2WYJHNHJE&lid=LSTREMHZ4K2WYJHNHJEI0ADM0&marketplace=FLIPKART&store=j9e&srno=b_1_9&otracker=browse&fm=organic&iid=9ee4cd9c-6a78-4cd3-874f-85b5477e5524.REMHZ4K2WYJHNHJE.SEARCH&ppt=None&ppn=None&ssid=0n0jcufd1c0000001782980983280&ov_redirect=true&ov_redirect=true",
      "scraped_at": "2026-07-02T08:29:45.178027",
      "quick_analysis": {
        "quick_score": 80,
        "top_pros": [
          "Multi-Function",
          "LCD Display"
        ],
        "top_con": "No reviews",
        "quick_verdict": "Worth checking"
      }
    },
    {
      "name": "Anish tech MPEG free dish set up box remote Free dish R...",
      "price": 189,
      "category": "Home_Kitchen",
      "image_url": "https://rukminim2.flixcart.com/image/612/612/xif0q/remote-controller/j/j/n/mpeg-free-dish-set-up-box-remote-anish-tech-original-imahz7sxfzmrptgu.jpeg?q=70",
      "flipkart_url": "https://www.flipkart.com/anish-tech-mpeg-free-dish-set-up-box-remote-controller/p/itm1af0cd5dd9d7f?pid=REMHZ7SXFQFWHRWM&lid=LSTREMHZ7SXFQFWHRWM3URW3D&marketplace=FLIPKART&store=j9e&srno=b_1_10&otracker=browse&fm=organic&iid=9ee4cd9c-6a78-4cd3-874f-85b5477e5524.REMHZ7SXFQFWHRWM.SEARCH&ppt=None&ppn=None&ssid=0n0jcufd1c0000001782980983280&ov_redirect=true&ov_redirect=true",
      "scraped_at": "2026-07-02T08:29:45.178254",
      "quick_analysis": {
        "quick_score": 80,
        "top_pros": [
          "Affordable price",
          "Easy setup"
        ],
        "top_con": "No reviews",
        "quick_verdict": "Worth checking"
      }
    },
    {
      "name": "DARYUE Maroon Matte Crayon Lipstick Long Stay Bold Fini...",
      "price": null,
      "category": "Beauty",
      "image_url": "https://rukminim2.flixcart.com/image/612/612/xif0q/lipstick/q/t/p/1-5-maroon-matte-crayon-lipstick-long-stay-waterproof-smudge-original-imahzwabmvvjztzt.jpeg?q=70",
      "flipkart_url": "https://www.flipkart.com/daryue-maroon-matte-crayon-lipstick-long-stay-bold-finish/p/itmf29d2adb7ffbd?pid=LSKHZX6JCXCXJMT8&store=g9b%2Fffi&srno=b_1_1&otracker=browse&fm=organic&iid=1075dc31-63b5-43f9-844b-653252ed90ba.LSKHZX6JCXCXJMT8.SEARCH&ppt=None&ppn=None&ssid=gr71pegy4g0000001782980989013&ov_redirect=true&ov_redirect=true",
      "scraped_at": "2026-07-02T08:29:50.660080",
      "quick_analysis": {
        "quick_score": 80,
        "top_pros": [
          "Long Lasting",
          "Bold Color"
        ],
        "top_con": "No Reviews",
        "quick_verdict": "Wait for more data"
      }
    },
    {
      "name": "voorkoms Luxury Bloom Garden Mehndi Stencil Sticker Col...",
      "price": null,
      "category": "Beauty",
      "image_url": "https://rukminim2.flixcart.com/image/612/612/xif0q/tattoo/b/t/s/6-6-v-ms-1751-1759-voorkoms-11-original-imahzx5hhq8wzwup.jpeg?q=70",
      "flipkart_url": "https://www.flipkart.com/voorkoms-luxury-bloom-garden-mehndi-stencil-sticker-collection-artistic-hand-art/p/itmf07b67f27010d?pid=TTTHZX5HQZBUGN6A&store=g9b%2Fffi&srno=b_1_2&otracker=browse&fm=organic&iid=1075dc31-63b5-43f9-844b-653252ed90ba.TTTHZX5HQZBUGN6A.SEARCH&ppt=None&ppn=None&ssid=gr71pegy4g0000001782980989013&ov_redirect=true&ov_redirect=true",
      "scraped_at": "2026-07-02T08:29:50.660394",
      "quick_analysis": {
        "quick_score": 80,
        "top_pros": [
          "Easy to use",
          "Artistic designs"
        ],
        "top_con": "Limited reviews",
        "quick_verdict": "Worth checking"
      }
    },
    {
      "name": "LUXURY TOUCH COSMETICS 3in1 concealer best gr57 Conceal...",
      "price": null,
      "category": "Beauty",
      "image_url": "https://rukminim2.flixcart.com/image/612/612/xif0q/concealer/3/a/p/12-3in1-concealer-best-gr57-luxury-touch-cosmetics-original-imahzx6ezny7qhgu.jpeg?q=70",
      "flipkart_url": "https://www.flipkart.com/luxury-touch-cosmetics-3in1-concealer-best-gr57/p/itme5ae1c42532da?pid=CLRHZX6EZVGUU25P&store=g9b%2Fffi&srno=b_1_3&otracker=browse&fm=organic&iid=1075dc31-63b5-43f9-844b-653252ed90ba.CLRHZX6EZVGUU25P.SEARCH&ppt=None&ppn=None&ssid=gr71pegy4g0000001782980989013&ov_redirect=true&ov_redirect=true",
      "scraped_at": "2026-07-02T08:29:50.660696",
      "quick_analysis": {
        "quick_score": 70,
        "top_pros": [
          "Natural Shade",
          "3in1 Formula"
        ],
        "top_con": "Limited Reviews",
        "quick_verdict": "Wait for more data"
      }
    },
    {
      "name": "Neycare 3D Hydrating Lip Oil | Moisturizing, Non-Sticky",
      "price": null,
      "category": "Beauty",
      "image_url": "https://rukminim2.flixcart.com/image/612/612/xif0q/lip-gloss/3/p/0/18-3d-hydrating-lip-oil-moisturizing-non-sticky-felicechiara-original-imahzw9gjmwhyeen.jpeg?q=70",
      "flipkart_url": "https://www.flipkart.com/neycare-3d-hydrating-lip-oil-moisturizing-non-sticky/p/itme77333a1e250a?pid=LGSHZX7GJPZ7CMPC&store=g9b%2Fffi&srno=b_1_4&otracker=browse&fm=organic&iid=1075dc31-63b5-43f9-844b-653252ed90ba.LGSHZX7GJPZ7CMPC.SEARCH&ppt=None&ppn=None&ssid=gr71pegy4g0000001782980989013&ov_redirect=true&ov_redirect=true",
      "scraped_at": "2026-07-02T08:29:50.661037",
      "quick_analysis": {
        "quick_score": 80,
        "top_pros": [
          "Moisturizing",
          "Non-Sticky"
        ],
        "top_con": "Limited reviews",
        "quick_verdict": "Worth checking"
      }
    },
    {
      "name": "Givni Mart Travel Mini Foldable Compact Square Design B...",
      "price": 256,
      "category": "Beauty",
      "image_url": "https://rukminim2.flixcart.com/image/612/612/xif0q/compact-mirror/f/r/v/2-foldable-compact-beauty-makeup-pocket-mirror-square-sqr-original-imahjhnrrupzhttk.jpeg?q=70",
      "flipkart_url": "https://www.flipkart.com/givni-mart-travel-mini-foldable-compact-square-design-beauty-makeup-pocket-mirror/p/itmd6a680c717e84?pid=CTMHJNRMTRE57THH&lid=LSTCTMHJNRMTRE57THH0C4QLW&marketplace=FLIPKART&store=g9b%2Fffi&srno=b_1_5&otracker=browse&fm=organic&iid=1075dc31-63b5-43f9-844b-653252ed90ba.CTMHJNRMTRE57THH.SEARCH&ppt=None&ppn=None&ssid=gr71pegy4g0000001782980989013&ov_redirect=true&ov_redirect=true",
      "scraped_at": "2026-07-02T08:29:50.661273",
      "quick_analysis": {
        "quick_score": 80,
        "top_pros": [
          "Compact Design",
          "Portable Mirror"
        ],
        "top_con": "Limited Reviews",
        "quick_verdict": "Worth checking"
      }
    },
    {
      "name": "Ordershock Creative Watch Art & Mandala Mehndi Stencil ...",
      "price": null,
      "category": "Beauty",
      "image_url": "https://rukminim2.flixcart.com/image/612/612/xif0q/tattoo/k/a/t/6-6-v-1821-1822-1823-1824-voorkoms-11-original-imahzm9pnnmv5j2v.jpeg?q=70",
      "flipkart_url": "https://www.flipkart.com/ordershock-creative-watch-art-mandala-mehndi-stencil-sticker-combo-pack-full-hand/p/itmc1119a88ca574?pid=TTTHZX6WTYYTBN6M&store=g9b%2Fffi&srno=b_1_6&otracker=browse&fm=organic&iid=1075dc31-63b5-43f9-844b-653252ed90ba.TTTHZX6WTYYTBN6M.SEARCH&ppt=None&ppn=None&ssid=gr71pegy4g0000001782980989013&ov_redirect=true&ov_redirect=true",
      "scraped_at": "2026-07-02T08:29:50.661574",
      "quick_analysis": {
        "quick_score": 80,
        "top_pros": [
          "Unique Designs",
          "Easy Application"
        ],
        "top_con": "Limited Durability",
        "quick_verdict": "Worth checking"
      }
    },
    {
      "name": "Ordershock Traditional Mandala Mehndi Design Stencil St...",
      "price": null,
      "category": "Beauty",
      "image_url": "https://rukminim2.flixcart.com/image/612/612/xif0q/tattoo/w/t/t/6-6-v-1816-1817-1818-1819-voorkoms-11-original-imahzm9geyhfgxxw.jpeg?q=70",
      "flipkart_url": "https://www.flipkart.com/ordershock-traditional-mandala-mehndi-design-stencil-sticker-combo-pack-party-event/p/itmeaab5908a57ca?pid=TTTHZX72Z3YQQ6HN&store=g9b%2Fffi&srno=b_1_7&otracker=browse&fm=organic&iid=1075dc31-63b5-43f9-844b-653252ed90ba.TTTHZX72Z3YQQ6HN.SEARCH&ppt=None&ppn=None&ssid=gr71pegy4g0000001782980989013&ov_redirect=true&ov_redirect=true",
      "scraped_at": "2026-07-02T08:29:50.661874",
      "quick_analysis": {
        "quick_score": 80,
        "top_pros": [
          "Easy to use",
          "Mehndi designs"
        ],
        "top_con": "Limited details",
        "quick_verdict": "Worth checking"
      }
    },
    {
      "name": "AMOSFIA Perfect Shine finish Translucent Loose Setting ...",
      "price": null,
      "category": "Beauty",
      "image_url": "https://rukminim2.flixcart.com/image/612/612/xif0q/compact/d/u/u/15-perfect-shine-finish-translucent-loose-setting-powder-compact-original-imahzw9m9cs86zhg.jpeg?q=70",
      "flipkart_url": "https://www.flipkart.com/amosfia-perfect-shine-finish-translucent-loose-setting-powder-compact/p/itmf2eb14797c5b2?pid=CMPHZX72UHXCQEEM&store=g9b%2Fffi&srno=b_1_8&otracker=browse&fm=organic&iid=1075dc31-63b5-43f9-844b-653252ed90ba.CMPHZX72UHXCQEEM.SEARCH&ppt=None&ppn=None&ssid=gr71pegy4g0000001782980989013&ov_redirect=true&ov_redirect=true",
      "scraped_at": "2026-07-02T08:29:50.662214",
      "quick_analysis": {
        "quick_score": 80,
        "top_pros": [
          "Natural Finish",
          "SPF Protection"
        ],
        "top_con": "Limited Shades",
        "quick_verdict": "Worth checking"
      }
    },
    {
      "name": "AMOSFIA Skin Glow Ultra Fine Loose Setting Powder  Comp...",
      "price": null,
      "category": "Beauty",
      "image_url": "https://rukminim2.flixcart.com/image/612/612/xif0q/compact/v/s/7/15-skin-glow-ultra-fine-loose-setting-powder-compact-original-imahzwb9etvknzvp.jpeg?q=70",
      "flipkart_url": "https://www.flipkart.com/amosfia-skin-glow-ultra-fine-loose-setting-powder-compact/p/itm618726b2cf1f7?pid=CMPHZX73DTNYFPGX&store=g9b%2Fffi&srno=b_1_9&otracker=browse&fm=organic&iid=1075dc31-63b5-43f9-844b-653252ed90ba.CMPHZX73DTNYFPGX.SEARCH&ppt=None&ppn=None&ssid=gr71pegy4g0000001782980989013&ov_redirect=true&ov_redirect=true",
      "scraped_at": "2026-07-02T08:29:50.662516",
      "quick_analysis": {
        "quick_score": 80,
        "top_pros": [
          "Fine Texture",
          "Natural Shade"
        ],
        "top_con": "Limited Reviews",
        "quick_verdict": "Worth checking"
      }
    },
    {
      "name": "Velissa paris Concealer Natural Pro Concealer Palette-C...",
      "price": null,
      "category": "Beauty",
      "image_url": "https://rukminim2.flixcart.com/image/612/612/xif0q/concealer/9/t/u/22-concealer-natural-pro-concealer-palette-corrector-concealer-original-imahzx667d2hgmzn.jpeg?q=70",
      "flipkart_url": "https://www.flipkart.com/velissa-paris-concealer-natural-pro-palette-corrector-six-one-xb15/p/itm9fe4dbb52b8f1?pid=CLRHZX664UEWT4ZZ&store=g9b%2Fffi&srno=b_1_10&otracker=browse&fm=organic&iid=1075dc31-63b5-43f9-844b-653252ed90ba.CLRHZX664UEWT4ZZ.SEARCH&ppt=None&ppn=None&ssid=gr71pegy4g0000001782980989013&ov_redirect=true&ov_redirect=true",
      "scraped_at": "2026-07-02T08:29:50.662817",
      "quick_analysis": {
        "quick_score": 80,
        "top_pros": [
          "Natural Finish",
          "Six in One"
        ],
        "top_con": "Limited Shades",
        "quick_verdict": "Worth checking"
      }
    }
  ]
}