{
  "date": "2026-07-19T07:42:21Z",
  "total_products": 10,
  "products": [
    {
      "name": "Blocked Printed, Floral Print, Printed Hand Batik Cotto...",
      "price": 414,
      "category": "Fashion",
      "image_url": "https://rukminim2.flixcart.com/image/612/612/xif0q/sari/a/v/y/free-07-new-km-new-06-sunflower-firoji-black-saree-for-women-original-imahpf9uz5zyrcwj.jpeg?q=70",
      "flipkart_url": "https://www.flipkart.com/kamalkunj-designer-blocked-printed-floral-print-printed-hand-batik-cotton-silk-saree/p/itm0e91c9c22cea0?pid=SARHPFZJ4HY9QYAB&lid=LSTSARHPFZJ4HY9QYABQNNSJP&marketplace=FLIPKART&store=clo&srno=b_1_1&otracker=browse&fm=organic&iid=fe5cde02-ffe4-4278-9255-8fe18cce245b.SARHPFZJ4HY9QYAB.SEARCH&ppt=None&ppn=None&ssid=kj40wvt2ww0000001784446844916&ov_redirect=true",
      "scraped_at": "2026-07-19T07:40:47.736760",
      "quick_analysis": {
        "quick_score": 80,
        "top_pros": [
          "Floral Print",
          "Affordable Price"
        ],
        "top_con": "No Reviews",
        "quick_verdict": "Worth checking"
      }
    },
    {
      "name": "AFWAL Hanki For Man [\"White\"] Handkerchief",
      "price": 88,
      "category": "Fashion",
      "image_url": "https://rukminim2.flixcart.com/image/612/612/xif0q/handkerchief/7/o/b/hanki-for-man-5-formal-af001-afwal-original-imahp79w5uxdtrca.jpeg?q=70",
      "flipkart_url": "https://www.flipkart.com/afwal-hanki-man-white-handkerchief/p/itm9daec4cac3b5d?pid=HKFHP79WWZ7BZ9BT&lid=LSTHKFHP79WWZ7BZ9BTBDDU6U&marketplace=FLIPKART&store=clo&srno=b_1_2&otracker=browse&fm=organic&iid=fe5cde02-ffe4-4278-9255-8fe18cce245b.HKFHP79WWZ7BZ9BT.SEARCH&ppt=None&ppn=None&ssid=kj40wvt2ww0000001784446844916&ov_redirect=true",
      "scraped_at": "2026-07-19T07:40:47.736998",
      "quick_analysis": {
        "quick_score": 80,
        "top_pros": [
          "Good quality",
          "Affordable price"
        ],
        "top_con": "No reviews",
        "quick_verdict": "Worth checking"
      }
    },
    {
      "name": "Men & Women Straight Full Sleeve Multicolor Shrug",
      "price": 699,
      "category": "Fashion",
      "image_url": "https://rukminim2.flixcart.com/image/612/612/xif0q/shrug/0/s/a/xl-1-10-trsuil-white-king-black-shurg-combo-xl-4-jks-payout-original-imahzgw6vqauykha.jpeg?q=70",
      "flipkart_url": "https://www.flipkart.com/rd-fashion-men-women-shrug/p/itm95f7d6e2572e5?pid=RUGHZGWC4FZDGYKJ&lid=LSTRUGHZGWC4FZDGYKJPMFM8X&marketplace=FLIPKART&store=clo&srno=b_1_3&otracker=browse&fm=organic&iid=fe5cde02-ffe4-4278-9255-8fe18cce245b.RUGHZGWC4FZDGYKJ.SEARCH&ppt=None&ppn=None&ssid=kj40wvt2ww0000001784446844916&ov_redirect=true",
      "scraped_at": "2026-07-19T07:40:47.737201",
      "quick_analysis": {
        "quick_score": 80,
        "top_pros": [
          "Multicolor option",
          "Full sleeve"
        ],
        "top_con": "Price concern",
        "quick_verdict": "Worth checking"
      }
    },
    {
      "name": "Men & Women Half Sleeve White Shrug",
      "price": 699,
      "category": "Fashion",
      "image_url": "https://rukminim2.flixcart.com/image/612/612/xif0q/shrug/w/q/t/xl-1-jai-shree-ram-10-trsuil-shurg-white-combo-xl-4-jks-payout-original-imahzgw6uyetmwgn.jpeg?q=70",
      "flipkart_url": "https://www.flipkart.com/jks-fashion-men-women-shrug/p/itm15b5dac3251e9?pid=RUGHZMHMJYGZKYFX&lid=LSTRUGHZMHMJYGZKYFXLS7FFQ&marketplace=FLIPKART&store=clo&srno=b_1_4&otracker=browse&fm=organic&iid=fe5cde02-ffe4-4278-9255-8fe18cce245b.RUGHZMHMJYGZKYFX.SEARCH&ppt=None&ppn=None&ssid=kj40wvt2ww0000001784446844916&ov_redirect=true",
      "scraped_at": "2026-07-19T07:40:47.737401",
      "quick_analysis": {
        "quick_score": 80,
        "top_pros": [
          "Good Quality",
          "Affordable Price"
        ],
        "top_con": "Limited Reviews",
        "quick_verdict": "Worth checking"
      }
    },
    {
      "name": "Round Neck Women Blouse",
      "price": 210,
      "category": "Fashion",
      "image_url": "https://rukminim2.flixcart.com/image/612/612/xif0q/blouse/g/t/u/32-geminipremiuma-ahriz-original-imahkdsp67yy2c4g.jpeg?q=70",
      "flipkart_url": "https://www.flipkart.com/ahriz-round-neck-women-blouse/p/itm97dbb03e3608e?pid=BLOHKD76XDPZ4MSM&lid=LSTBLOHKD76XDPZ4MSM8Y2EPU&marketplace=FLIPKART&store=clo&srno=b_1_5&otracker=browse&fm=organic&iid=fe5cde02-ffe4-4278-9255-8fe18cce245b.BLOHKD76XDPZ4MSM.SEARCH&ppt=None&ppn=None&ssid=kj40wvt2ww0000001784446844916&ov_redirect=true",
      "scraped_at": "2026-07-19T07:40:47.737593",
      "quick_analysis": {
        "quick_score": 79,
        "top_pros": [
          "Good Quality",
          "Affordable Price"
        ],
        "top_con": "Size Issues",
        "quick_verdict": "Worth checking"
      }
    },
    {
      "name": "Floral Print Pure Cotton Straight Kurta for Women",
      "price": 268,
      "category": "Fashion",
      "image_url": "https://rukminim2.flixcart.com/image/612/612/xif0q/kurta/g/9/r/xs-shortkurti-22-saadgee-original-imahnjakm8aywgf4.jpeg?q=70",
      "flipkart_url": "https://www.flipkart.com/pahirava-women-floral-print-straight-kurta/p/itm09e74f4e2fe57?pid=KTAHPF6ZSWWRD7ZP&lid=LSTKTAHPF6ZSWWRD7ZPWT6HDL&marketplace=FLIPKART&store=clo&srno=b_1_6&otracker=browse&fm=organic&iid=fe5cde02-ffe4-4278-9255-8fe18cce245b.KTAHPF6ZSWWRD7ZP.SEARCH&ppt=None&ppn=None&ssid=kj40wvt2ww0000001784446844916&ov_redirect=true",
      "scraped_at": "2026-07-19T07:40:47.737774",
      "quick_analysis": {
        "quick_score": 80,
        "top_pros": [
          "Pure Cotton",
          "Affordable Price"
        ],
        "top_con": "Out of Stock",
        "quick_verdict": "Worth checking"
      }
    },
    {
      "name": "Girls Casual Top Shorts",
      "price": 448,
      "category": "Fashion",
      "image_url": "https://rukminim2.flixcart.com/image/612/612/xif0q/kids-apparel-combo/y/6/u/6-9-months-htsh5bzdd-aanikids-original-imahpf5gun2xzx7y.jpeg?q=70",
      "flipkart_url": "https://www.flipkart.com/ayat-fashion-girls-casual-top-shorts/p/itmfff63e7c3c945?pid=KPBHPF63FWN3PYEZ&lid=LSTKPBHPF63FWN3PYEZFLAPBX&marketplace=FLIPKART&store=clo&srno=b_1_7&otracker=browse&fm=organic&iid=fe5cde02-ffe4-4278-9255-8fe18cce245b.KPBHPF63FWN3PYEZ.SEARCH&ppt=None&ppn=None&ssid=kj40wvt2ww0000001784446844916&ov_redirect=true",
      "scraped_at": "2026-07-19T07:40:47.737979",
      "quick_analysis": {
        "quick_score": 80,
        "top_pros": [
          "Good quality",
          "Affordable price"
        ],
        "top_con": "Size issues",
        "quick_verdict": "Worth checking"
      }
    },
    {
      "name": "Men Relaxed Cream Linen Blend Trousers",
      "price": 620,
      "category": "Fashion",
      "image_url": "https://rukminim2.flixcart.com/image/612/612/xif0q/trouser/g/w/z/34-cutoff-linen-cream-cutd-original-imahpf6zz6pgfdyt.jpeg?q=70",
      "flipkart_url": "https://www.flipkart.com/cutd-relaxed-men-cream-trousers/p/itm18960edf69ae7?pid=TROHPF7FZ6RBFKGU&lid=LSTTROHPF7FZ6RBFKGULWN47J&marketplace=FLIPKART&store=clo&srno=b_1_8&otracker=browse&fm=organic&iid=fe5cde02-ffe4-4278-9255-8fe18cce245b.TROHPF7FZ6RBFKGU.SEARCH&ppt=None&ppn=None&ssid=kj40wvt2ww0000001784446844916&ov_redirect=true",
      "scraped_at": "2026-07-19T07:40:47.738174",
      "quick_analysis": {
        "quick_score": 80,
        "top_pros": [
          "Comfortable fit",
          "Linen blend"
        ],
        "top_con": "Price concern",
        "quick_verdict": "Worth checking"
      }
    },
    {
      "name": "Printed Couple T-shirts Twinning Set",
      "price": 699,
      "category": "Fashion",
      "image_url": "https://rukminim2.flixcart.com/image/612/612/xif0q/twinning-set/a/y/m/xl-xl-oshsmaroonpg4-na-na-twinny-zone-men-women-original-imahpfmtuen5jkfs.jpeg?q=70",
      "flipkart_url": "https://www.flipkart.com/twinny-zone-printed-couple-t-shirts-twinning-set/p/itm719049dd48613?pid=TGQHPFMUFQGJZVPH&lid=LSTTGQHPFMUFQGJZVPHY73XHA&marketplace=FLIPKART&store=clo&srno=b_1_9&otracker=browse&fm=organic&iid=fe5cde02-ffe4-4278-9255-8fe18cce245b.TGQHPFMUFQGJZVPH.SEARCH&ppt=None&ppn=None&ssid=kj40wvt2ww0000001784446844916&ov_redirect=true",
      "scraped_at": "2026-07-19T07:40:47.738356",
      "quick_analysis": {
        "quick_score": 80,
        "top_pros": [
          "New Arrival",
          "Couple Set"
        ],
        "top_con": "No Reviews",
        "quick_verdict": "Worth checking"
      }
    },
    {
      "name": "Men Brief",
      "price": 425,
      "category": "Fashion",
      "image_url": "https://rukminim2.flixcart.com/image/612/612/xif0q/shopsy-brief/b/d/l/s-1-soyi-07611-rbl-wh-s-brief-feelingas-trend-original-imahn8d6bz2njs6k.jpeg?q=70",
      "flipkart_url": "https://www.flipkart.com/lingenears-trend-men-brief/p/itm1b0ca48864c4e?pid=BRFHPF5ZAJKGUHZU&lid=LSTBRFHPF5ZAJKGUHZUUMRYCQ&marketplace=FLIPKART&store=clo&srno=b_1_10&otracker=browse&fm=organic&iid=fe5cde02-ffe4-4278-9255-8fe18cce245b.BRFHPF5ZAJKGUHZU.SEARCH&ppt=None&ppn=None&ssid=kj40wvt2ww0000001784446844916&ov_redirect=true",
      "scraped_at": "2026-07-19T07:40:47.738531",
      "quick_analysis": {
        "quick_score": 80,
        "top_pros": [
          "Good Quality",
          "Comfortable Fit"
        ],
        "top_con": "Price Concern",
        "quick_verdict": "Worth checking"
      }
    }
  ]
}